setup.py
bigsec_mod1.egg-info/PKG-INFO
bigsec_mod1.egg-info/SOURCES.txt
bigsec_mod1.egg-info/dependency_links.txt
bigsec_mod1.egg-info/top_level.txt
bigsec_mod1.egg-info/zip-safe
bigsec_print/__init__.py
bigsec_print/test.py