Metadata-Version: 1.0
Name: bigsec-mod1
Version: 0.2.0
Summary: a first module
Home-page: http://v2.bigsec.com
Author: wxt
Author-email: xt.wang@bigsec.com
License: MIT
Keywords: bigsec security
Platform: UNKNOWN
